LICENSE
MANIFEST.in
README.md
ffi.py
pyproject.toml
setup.py
uringloop/__init__.py
uringloop/_liburing.abi3.so
uringloop/_liburing.c
uringloop/_liburing.cpython-312-x86_64-linux-gnu.so
uringloop/_liburing.o
uringloop/_liburing.pyi
uringloop/lib.py
uringloop/log.py
uringloop/loop.py
uringloop/operation.py
uringloop/proactor.py
uringloop/py.typed
uringloop.egg-info/PKG-INFO
uringloop.egg-info/SOURCES.txt
uringloop.egg-info/dependency_links.txt
uringloop.egg-info/requires.txt
uringloop.egg-info/top_level.txt