Metadata-Version: 2.4
Name: uringloop
Version: 0.1.0
Project-URL: Homepage, https://github.com/bright2227/uringloop
Requires-Python: >=3.12
License-File: LICENSE
Requires-Dist: cffi>=1.17.1
Requires-Dist: setuptools>=78.1.0
Dynamic: license-file
